README.md
setup.py
william_blake_crypto/__init__.py
william_blake_crypto.egg-info/PKG-INFO
william_blake_crypto.egg-info/SOURCES.txt
william_blake_crypto.egg-info/dependency_links.txt
william_blake_crypto.egg-info/not-zip-safe
william_blake_crypto.egg-info/requires.txt
william_blake_crypto.egg-info/top_level.txt