Metadata-Version: 1.2
Name: william-blake-crypto
Version: 2019.4.3.617
Summary: cryptography library
Home-page: https://github.com/wdbm/william_blake_crypto
Author: Will Breaden Madden
Author-email: wbm@protonmail.ch
License: GPLv3
Platform: UNKNOWN
Requires-Python: >=3
